[[0,["start",{"collapsed":false,"xcor":0,"ycor":-1.8369701987210297e-14,"heading":0,"color":50,"shade":60,"pensize":5,"grey":200}],455,100,[null,1,null]],[1,["forward",{}],469,141,[0,2,3]],[2,["number",{"value":100}],555,141,[1]],[3,["right",{}],469,173,[1,4,5]],[4,["number",{"value":90}],552,173,[3]],[5,["setcolor",{}],469,205,[3,6,7]],[6,["number",{"value":90}],558,205,[5]],[7,["forward",{}],469,237,[5,8,9]],[8,["number",{"value":100}],555,237,[7]],[9,["right",{}],469,269,[7,10,11]],[10,["number",{"value":90}],552,269,[9]],[11,["setcolor",{}],469,301,[9,12,13]],[12,["number",{"value":80}],558,301,[11]],[13,["forward",{}],469,333,[11,14,15]],[14,["number",{"value":100}],555,333,[13]],[15,["right",{}],469,365,[13,16,17]],[16,["number",{"value":90}],552,365,[15]],[17,["setcolor",{}],469,397,[15,18,19]],[18,["number",{"value":50}],558,397,[17]],[19,["forward",{}],469,429,[17,20,21]],[20,["number",{"value":100}],555,429,[19]],[21,["right",{}],469,461,[19,22,null]],[22,["number",{"value":90}],552,461,[21]]]